omnivorex/__init__.py
omnivorex/omnivorex.py
omnivorex/utils.py
omnivorex/components/__init__.py
omnivorex/components/article_item.py
omnivorex/components/login_screen.py
omnivorex-0.0.15.dist-info/LICENSE
omnivorex-0.0.15.dist-info/METADATA
omnivorex-0.0.15.dist-info/WHEEL
omnivorex-0.0.15.dist-info/entry_points.txt
omnivorex-0.0.15.dist-info/top_level.txt
omnivorex-0.0.15.dist-info/RECORD
