Metadata-Version: 2.1
Name: omnivorex
Version: 0.0.15
Summary: Omnivore Terminal App - Text User Interface
Home-page: https://github.com/yazdipour/OmnivoreX
Author: Shahriar Yazdipour
Author-email: git@yazdipour.com
License: MIT
Project-URL: Bug Tracker, https://github.com/yazdipour/OmnivoreX/issues
Project-URL: Source Code, https://github.com/yazdipour/OmnivoreX
Keywords: omnivore cli terminal readlater client tui rich textualize textual
Classifier: Programming Language :: Python :: 3
Classifier: Operating System :: OS Independent
Classifier: Programming Language :: Python :: 3
Classifier: License :: OSI Approved :: MIT License
Requires-Python: >=3
License-File: LICENSE
Requires-Dist: python-dotenv
Requires-Dist: omnivoreql (>=0.2.1)
Requires-Dist: textual (==0.29.0)
